AUTHORS
LICENCE
MANIFEST.in
README
setup.py
doc/MODULES.documentation
doc/__init__.py
doc/classes.dot
doc/pydoctor.cfg
doc/references.dot
doc/root-parent-references.dot
doc/structure.dot
doc/structure.svg
doc/api/apidocs.css
doc/api/moduleindex.html
doc/api/otfbot.__init__.html
doc/api/otfbot.html
doc/api/otfbot.lib.__init__.html
doc/api/otfbot.lib.chatMod.chatMod.html
doc/api/otfbot.lib.chatMod.html
doc/api/otfbot.lib.eliza.eliza.html
doc/api/otfbot.lib.eliza.html
doc/api/otfbot.lib.functions.html
doc/api/otfbot.lib.html
doc/api/otfbot.lib.pluginSupport.__init__.html
doc/api/otfbot.lib.pluginSupport.decorators.html
doc/api/otfbot.lib.pluginSupport.html
doc/api/otfbot.lib.pluginSupport.plSupport.html
doc/api/otfbot.lib.pluginSupport.plSupport.pluginSupport.WontStart.html
doc/api/otfbot.lib.pluginSupport.plSupport.pluginSupport.html
doc/api/otfbot.lib.pyniall_sqlite.html
doc/api/otfbot.lib.pyniall_sqlite.pyNiall.html
doc/api/otfbot.lib.urlutils.html
doc/api/otfbot.lib.user.BotUser.html
doc/api/otfbot.lib.user.IrcUser.html
doc/api/otfbot.lib.user.html
doc/api/otfbot.lib.vername.Ver2NameTestCase.html
doc/api/otfbot.lib.vername.html
doc/api/otfbot.lib.version.GitVersion.html
doc/api/otfbot.lib.version.html
doc/api/otfbot.plugins.__init__.html
doc/api/otfbot.plugins.html
doc/api/otfbot.plugins.ircClient.__init__.html
doc/api/otfbot.plugins.ircClient.answers.Plugin.html
doc/api/otfbot.plugins.ircClient.answers.html
doc/api/otfbot.plugins.ircClient.auth.Plugin.html
doc/api/otfbot.plugins.ircClient.auth.html
doc/api/otfbot.plugins.ircClient.autorejoin.Plugin.html
doc/api/otfbot.plugins.ircClient.autorejoin.html
doc/api/otfbot.plugins.ircClient.badwords.Plugin.html
doc/api/otfbot.plugins.ircClient.badwords.html
doc/api/otfbot.plugins.ircClient.chapterbot.Plugin.html
doc/api/otfbot.plugins.ircClient.chapterbot.html
doc/api/otfbot.plugins.ircClient.commands.Plugin.html
doc/api/otfbot.plugins.ircClient.commands.html
doc/api/otfbot.plugins.ircClient.controlIRC.Plugin.html
otfbot.egg-info/PKG-INFO
otfbot.egg-info/SOURCES.txt
otfbot.egg-info/dependency_links.txt
otfbot.egg-info/requires.txt
otfbot.egg-info/top_level.txt
