Metadata-Version: 1.0
Name: otfbot
Version: 1.0.0
Summary: a modular IRC-Bot
Home-page: http://www.otfbot.org/
Author: Alexander Schier, Robert Weidlich, Thomas Wiegart
Author-email: otfbot-dev@list.otfbot.org
License: GPLv2
Download-URL: http://www.otfbot.org/files/otfbot-1.0.0.tar.gz
Platform: UNKNOWN
Classifier: Development Status :: 5 - Production/Stable
Classifier: Environment :: No Input/Output (Daemon)
Classifier: Framework :: Twisted
Classifier: Intended Audience :: End Users/Desktop
Classifier: License :: OSI Approved :: GNU General Public License (GPL)
Classifier: Operating System :: OS Independent
Classifier: Programming Language :: Python
Classifier: Programming Language :: Python :: 2.6
Classifier: Topic :: Communications :: Chat :: Internet Relay Chat
Classifier: Topic :: Games/Entertainment
